setup.cfg
setup.py
OrderCloud/__init__.py
OrderCloud/api_client.py
OrderCloud/configuration.py
OrderCloud/rest.py
OrderCloud.egg-info/PKG-INFO
OrderCloud.egg-info/SOURCES.txt
OrderCloud.egg-info/dependency_links.txt
OrderCloud.egg-info/requires.txt
OrderCloud.egg-info/top_level.txt
OrderCloud/apis/__init__.py
OrderCloud/apis/address_api.py
OrderCloud/apis/admin_address_api.py
OrderCloud/apis/admin_user_api.py
OrderCloud/apis/admin_user_group_api.py
OrderCloud/apis/approval_rule_api.py
OrderCloud/apis/auth_api.py
OrderCloud/apis/buyer_api.py
OrderCloud/apis/catalog_api.py
OrderCloud/apis/category_api.py
OrderCloud/apis/cost_center_api.py
OrderCloud/apis/credit_card_api.py
OrderCloud/apis/impersonation_config_api.py
OrderCloud/apis/line_item_api.py
OrderCloud/apis/me_api.py
OrderCloud/apis/message_senders_api.py
OrderCloud/apis/order_api.py
OrderCloud/apis/password_reset_api.py
OrderCloud/apis/payment_api.py
OrderCloud/apis/price_schedule_api.py
OrderCloud/apis/product_api.py
OrderCloud/apis/promotion_api.py
OrderCloud/apis/security_profile_api.py
OrderCloud/apis/shipment_api.py
OrderCloud/apis/spec_api.py
OrderCloud/apis/spending_account_api.py
OrderCloud/apis/supplier_api.py
OrderCloud/apis/supplier_user_api.py
OrderCloud/apis/supplier_user_group_api.py
OrderCloud/apis/user_api.py
OrderCloud/apis/user_group_api.py
OrderCloud/models/__init__.py
OrderCloud/models/access_token.py
OrderCloud/models/address.py
OrderCloud/models/address_assignment.py
OrderCloud/models/approval_rule.py
OrderCloud/models/base_spec.py
OrderCloud/models/buyer.py
OrderCloud/models/buyer_address.py
OrderCloud/models/buyer_credit_card.py
OrderCloud/models/buyer_product.py
OrderCloud/models/buyer_shipment.py
OrderCloud/models/buyer_spec.py
OrderCloud/models/catalog.py
OrderCloud/models/catalog_assignment.py
OrderCloud/models/category.py
OrderCloud/models/category_assignment.py
OrderCloud/models/category_product_assignment.py
OrderCloud/models/cost_center.py
OrderCloud/models/cost_center_assignment.py
OrderCloud/models/credit_card.py
OrderCloud/models/credit_card_assignment.py
OrderCloud/models/impersonate_token_request.py
