Metadata-Version: 1.0
Name: OrderCloud
Version: 1.0.57
Summary: OrderCloud
Home-page: http://ordercloud.io
Author: UNKNOWN
Author-email: ordercloud@four51.com
License: UNKNOWN
Keywords: Swagger,OrderCloud
Platform: UNKNOWN
